[
    {
        "bbox": [
            429.0,
            754.0,
            128.0,
            25.0
        ],
        "class": "Text"
    },
    {
        "bbox": [
            52.0,
            646.0,
            504.0,
            79.0
        ],
        "class": "Text"
    },
    {
        "bbox": [
            111.0,
            456.0,
            192.0,
            175.0
        ],
        "class": "Text"
    },
    {
        "bbox": [
            307.0,
            454.0,
            191.0,
            176.0
        ],
        "class": "Text"
    },
    {
        "bbox": [
            308.0,
            275.0,
            189.0,
            178.0
        ],
        "class": "Text"
    },
    {
        "bbox": [
            111.0,
            273.0,
            192.0,
            179.0
        ],
        "class": "Text"
    },
    {
        "bbox": [
            115.0,
            109.0,
            146.0,
            159.0
        ],
        "class": "Text"
    },
    {
        "bbox": [
            306.0,
            100.0,
            193.0,
            170.0
        ],
        "class": "Text"
    }
]