[
    {
        "bbox": [
            429.0,
            754.0,
            128.0,
            25.0
        ],
        "class": "Text"
    },
    {
        "bbox": [
            52.0,
            687.0,
            246.0,
            49.0
        ],
        "class": "Text"
    },
    {
        "bbox": [
            310.0,
            686.0,
            246.0,
            50.0
        ],
        "class": "Text"
    },
    {
        "bbox": [
            109.0,
            554.0,
            391.0,
            98.0
        ],
        "class": "Text"
    },
    {
        "bbox": [
            109.0,
            479.0,
            391.0,
            74.0
        ],
        "class": "Text"
    },
    {
        "bbox": [
            108.0,
            366.0,
            392.0,
            111.0
        ],
        "class": "Text"
    },
    {
        "bbox": [
            52.0,
            302.0,
            496.0,
            33.0
        ],
        "class": "Text"
    },
    {
        "bbox": [
            337.0,
            260.0,
            90.0,
            23.0
        ],
        "class": "Title"
    },
    {
        "bbox": [
            52.0,
            172.0,
            489.0,
            31.0
        ],
        "class": "Text"
    },
    {
        "bbox": [
            54.0,
            101.0,
            146.0,
            53.0
        ],
        "class": "Title"
    },
    {
        "bbox": [
            418.0,
            78.0,
            168.0,
            40.0
        ],
        "class": "Title"
    },
    {
        "bbox": [
            506.0,
            22.0,
            71.0,
            32.0
        ],
        "class": "Title"
    },
    {
        "bbox": [
            309.0,
            16.0,
            104.0,
            20.0
        ],
        "class": "Text"
    },
    {
        "bbox": [
            261.0,
            16.0,
            44.0,
            20.0
        ],
        "class": "Title"
    },
    {
        "bbox": [
            53.0,
            15.0,
            204.0,
            41.0
        ],
        "class": "Title"
    }
]