[
    {
        "bbox": [
            429.0,
            754.0,
            128.0,
            25.0
        ],
        "class": "Text"
    },
    {
        "bbox": [
            52.0,
            576.0,
            247.0,
            143.0
        ],
        "class": "Text"
    },
    {
        "bbox": [
            52.0,
            471.0,
            247.0,
            97.0
        ],
        "class": "Text"
    },
    {
        "bbox": [
            310.0,
            413.0,
            247.0,
            308.0
        ],
        "class": "Table"
    },
    {
        "bbox": [
            52.0,
            366.0,
            246.0,
            96.0
        ],
        "class": "Text"
    },
    {
        "bbox": [
            52.0,
            330.0,
            221.0,
            27.0
        ],
        "class": "Text"
    },
    {
        "bbox": [
            310.0,
            301.0,
            245.0,
            88.0
        ],
        "class": "Text"
    },
    {
        "bbox": [
            257.0,
            270.0,
            31.0,
            21.0
        ],
        "class": "Title"
    },
    {
        "bbox": [
            215.0,
            270.0,
            34.0,
            21.0
        ],
        "class": "Title"
    },
    {
        "bbox": [
            138.0,
            270.0,
            34.0,
            21.0
        ],
        "class": "Title"
    },
    {
        "bbox": [
            52.0,
            262.0,
            243.0,
            30.0
        ],
        "class": "Text"
    },
    {
        "bbox": [
            52.0,
            240.0,
            243.0,
            20.0
        ],
        "class": "Text"
    },
    {
        "bbox": [
            354.0,
            98.0,
            191.0,
            169.0
        ],
        "class": "Text"
    },
    {
        "bbox": [
            52.0,
            98.0,
            243.0,
            25.0
        ],
        "class": "Text"
    }
]