[
    {
        "bbox": [
            434.0,
            754.0,
            125.0,
            23.0
        ],
        "class": "Text"
    },
    {
        "bbox": [
            313.0,
            539.0,
            245.0,
            190.0
        ],
        "class": "Table"
    },
    {
        "bbox": [
            313.0,
            422.0,
            245.0,
            107.0
        ],
        "class": "Text"
    },
    {
        "bbox": [
            313.0,
            411.0,
            62.0,
            24.0
        ],
        "class": "Title"
    },
    {
        "bbox": [
            313.0,
            246.0,
            245.0,
            155.0
        ],
        "class": "Text"
    },
    {
        "bbox": [
            54.0,
            246.0,
            246.0,
            485.0
        ],
        "class": "Table"
    },
    {
        "bbox": [
            54.0,
            119.0,
            504.0,
            28.0
        ],
        "class": "Text"
    }
]