[
    {
        "bbox": [
            429.0,
            754.0,
            128.0,
            25.0
        ],
        "class": "Text"
    },
    {
        "bbox": [
            53.0,
            690.0,
            246.0,
            50.0
        ],
        "class": "Text"
    },
    {
        "bbox": [
            310.0,
            689.0,
            246.0,
            51.0
        ],
        "class": "Text"
    },
    {
        "bbox": [
            109.0,
            616.0,
            391.0,
            39.0
        ],
        "class": "Text"
    },
    {
        "bbox": [
            109.0,
            506.0,
            391.0,
            108.0
        ],
        "class": "Text"
    },
    {
        "bbox": [
            109.0,
            418.0,
            391.0,
            85.0
        ],
        "class": "Text"
    },
    {
        "bbox": [
            108.0,
            329.0,
            392.0,
            88.0
        ],
        "class": "Text"
    },
    {
        "bbox": [
            52.0,
            265.0,
            496.0,
            32.0
        ],
        "class": "Text"
    },
    {
        "bbox": [
            327.0,
            222.0,
            90.0,
            24.0
        ],
        "class": "Title"
    },
    {
        "bbox": [
            135.0,
            168.0,
            127.0,
            25.0
        ],
        "class": "Text"
    },
    {
        "bbox": [
            262.0,
            101.0,
            113.0,
            20.0
        ],
        "class": "Text"
    },
    {
        "bbox": [
            497.0,
            78.0,
            89.0,
            24.0
        ],
        "class": "Title"
    },
    {
        "bbox": [
            506.0,
            22.0,
            71.0,
            32.0
        ],
        "class": "Title"
    },
    {
        "bbox": [
            298.0,
            16.0,
            44.0,
            20.0
        ],
        "class": "Title"
    },
    {
        "bbox": [
            207.0,
            15.0,
            87.0,
            25.0
        ],
        "class": "Title"
    },
    {
        "bbox": [
            54.0,
            15.0,
            161.0,
            45.0
        ],
        "class": "Text"
    }
]