[
    {
        "bbox": [
            49.0,
            602.0,
            246.0,
            141.0
        ],
        "class": "Text"
    },
    {
        "bbox": [
            307.0,
            545.0,
            246.0,
            198.0
        ],
        "class": "Table"
    },
    {
        "bbox": [
            307.0,
            442.0,
            246.0,
            72.0
        ],
        "class": "Text"
    },
    {
        "bbox": [
            49.0,
            442.0,
            246.0,
            129.0
        ],
        "class": "Text"
    },
    {
        "bbox": [
            49.0,
            333.0,
            504.0,
            57.0
        ],
        "class": "Text"
    },
    {
        "bbox": [
            49.0,
            275.0,
            504.0,
            56.0
        ],
        "class": "Text"
    },
    {
        "bbox": [
            49.0,
            116.0,
            504.0,
            142.0
        ],
        "class": "Text"
    },
    {
        "bbox": [
            49.0,
            69.0,
            502.0,
            45.0
        ],
        "class": "Text"
    }
]