[
    {
        "bbox": [
            124.0,
            622.0,
            366.0,
            51.0
        ],
        "class": "Text"
    },
    {
        "bbox": [
            369.0,
            498.0,
            98.0,
            70.0
        ],
        "class": "Title"
    },
    {
        "bbox": [
            175.0,
            494.0,
            100.0,
            64.0
        ],
        "class": "Title"
    },
    {
        "bbox": [
            336.0,
            475.0,
            153.0,
            144.0
        ],
        "class": "Title"
    },
    {
        "bbox": [
            132.0,
            473.0,
            164.0,
            146.0
        ],
        "class": "Title"
    },
    {
        "bbox": [
            177.0,
            351.0,
            100.0,
            64.0
        ],
        "class": "Title"
    },
    {
        "bbox": [
            369.0,
            341.0,
            101.0,
            39.0
        ],
        "class": "Title"
    },
    {
        "bbox": [
            177.0,
            324.0,
            100.0,
            69.0
        ],
        "class": "Title"
    },
    {
        "bbox": [
            329.0,
            303.0,
            161.0,
            146.0
        ],
        "class": "Title"
    },
    {
        "bbox": [
            128.0,
            302.0,
            171.0,
            148.0
        ],
        "class": "Title"
    },
    {
        "bbox": [
            370.0,
            147.0,
            98.0,
            83.0
        ],
        "class": "Title"
    },
    {
        "bbox": [
            186.0,
            142.0,
            106.0,
            76.0
        ],
        "class": "Title"
    },
    {
        "bbox": [
            324.0,
            134.0,
            166.0,
            144.0
        ],
        "class": "Title"
    },
    {
        "bbox": [
            126.0,
            129.0,
            174.0,
            135.0
        ],
        "class": "Title"
    }
]