[
    {
        "bbox": [
            303.0,
            662.0,
            51.0,
            21.0
        ],
        "class": "Title"
    },
    {
        "bbox": [
            42.0,
            648.0,
            249.0,
            81.0
        ],
        "class": "Text"
    },
    {
        "bbox": [
            42.0,
            636.0,
            51.0,
            24.0
        ],
        "class": "Title"
    },
    {
        "bbox": [
            42.0,
            550.0,
            248.0,
            82.0
        ],
        "class": "Text"
    },
    {
        "bbox": [
            303.0,
            538.0,
            248.0,
            191.0
        ],
        "class": "Table"
    },
    {
        "bbox": [
            42.0,
            165.0,
            249.0,
            381.0
        ],
        "class": "Table"
    },
    {
        "bbox": [
            51.0,
            113.0,
            240.0,
            40.0
        ],
        "class": "Text"
    },
    {
        "bbox": [
            51.0,
            56.0,
            234.0,
            25.0
        ],
        "class": "Text"
    },
    {
        "bbox": [
            303.0,
            46.0,
            248.0,
            487.0
        ],
        "class": "Table"
    }
]