[
    {
        "bbox": [
            429.0,
            754.0,
            128.0,
            25.0
        ],
        "class": "Text"
    },
    {
        "bbox": [
            310.0,
            684.0,
            247.0,
            49.0
        ],
        "class": "Text"
    },
    {
        "bbox": [
            310.0,
            295.0,
            247.0,
            378.0
        ],
        "class": "Table"
    },
    {
        "bbox": [
            52.0,
            295.0,
            247.0,
            427.0
        ],
        "class": "Table"
    },
    {
        "bbox": [
            127.0,
            175.0,
            67.0,
            42.0
        ],
        "class": "Title"
    },
    {
        "bbox": [
            491.0,
            174.0,
            36.0,
            44.0
        ],
        "class": "Title"
    },
    {
        "bbox": [
            219.0,
            174.0,
            123.0,
            44.0
        ],
        "class": "Title"
    },
    {
        "bbox": [
            57.0,
            174.0,
            57.0,
            64.0
        ],
        "class": "Title"
    },
    {
        "bbox": [
            219.0,
            135.0,
            118.0,
            33.0
        ],
        "class": "Title"
    },
    {
        "bbox": [
            127.0,
            135.0,
            39.0,
            31.0
        ],
        "class": "Title"
    },
    {
        "bbox": [
            491.0,
            134.0,
            36.0,
            34.0
        ],
        "class": "Title"
    },
    {
        "bbox": [
            384.0,
            134.0,
            93.0,
            82.0
        ],
        "class": "Text"
    }
]