[
    {
        "bbox": [
            429.0,
            754.0,
            128.0,
            25.0
        ],
        "class": "Text"
    },
    {
        "bbox": [
            310.0,
            635.0,
            247.0,
            98.0
        ],
        "class": "Text"
    },
    {
        "bbox": [
            52.0,
            624.0,
            247.0,
            95.0
        ],
        "class": "Text"
    },
    {
        "bbox": [
            310.0,
            447.0,
            247.0,
            180.0
        ],
        "class": "Table"
    },
    {
        "bbox": [
            52.0,
            342.0,
            247.0,
            271.0
        ],
        "class": "Table"
    },
    {
        "bbox": [
            310.0,
            259.0,
            247.0,
            180.0
        ],
        "class": "Table"
    },
    {
        "bbox": [
            52.0,
            84.0,
            247.0,
            249.0
        ],
        "class": "Table"
    },
    {
        "bbox": [
            310.0,
            83.0,
            247.0,
            168.0
        ],
        "class": "Table"
    }
]