[
    {
        "bbox": [
            429.0,
            754.0,
            128.0,
            25.0
        ],
        "class": "Text"
    },
    {
        "bbox": [
            52.0,
            657.0,
            502.0,
            58.0
        ],
        "class": "Text"
    },
    {
        "bbox": [
            105.0,
            434.0,
            402.0,
            214.0
        ],
        "class": "Table"
    },
    {
        "bbox": [
            103.0,
            93.0,
            172.0,
            288.0
        ],
        "class": "Text"
    },
    {
        "bbox": [
            305.0,
            89.0,
            199.0,
            324.0
        ],
        "class": "Text"
    }
]