[
    {
        "bbox": [
            429.0,
            754.0,
            128.0,
            25.0
        ],
        "class": "Text"
    },
    {
        "bbox": [
            264.0,
            655.0,
            36.0,
            21.0
        ],
        "class": "Title"
    },
    {
        "bbox": [
            222.0,
            655.0,
            36.0,
            21.0
        ],
        "class": "Title"
    },
    {
        "bbox": [
            176.0,
            655.0,
            36.0,
            21.0
        ],
        "class": "Title"
    },
    {
        "bbox": [
            134.0,
            655.0,
            35.0,
            21.0
        ],
        "class": "Title"
    },
    {
        "bbox": [
            91.0,
            639.0,
            38.0,
            75.0
        ],
        "class": "Title"
    },
    {
        "bbox": [
            52.0,
            584.0,
            505.0,
            24.0
        ],
        "class": "Text"
    },
    {
        "bbox": [
            52.0,
            549.0,
            505.0,
            30.0
        ],
        "class": "Text"
    },
    {
        "bbox": [
            310.0,
            412.0,
            246.0,
            109.0
        ],
        "class": "Text"
    },
    {
        "bbox": [
            52.0,
            412.0,
            247.0,
            109.0
        ],
        "class": "Text"
    },
    {
        "bbox": [
            90.0,
            188.0,
            53.0,
            195.0
        ],
        "class": "Text"
    },
    {
        "bbox": [
            52.0,
            133.0,
            505.0,
            24.0
        ],
        "class": "Text"
    },
    {
        "bbox": [
            52.0,
            98.0,
            505.0,
            30.0
        ],
        "class": "Text"
    }
]