[
    {
        "bbox": [
            54.0,
            754.0,
            125.0,
            22.0
        ],
        "class": "Text"
    },
    {
        "bbox": [
            54.0,
            680.0,
            245.0,
            51.0
        ],
        "class": "Text"
    },
    {
        "bbox": [
            54.0,
            622.0,
            245.0,
            48.0
        ],
        "class": "Text"
    },
    {
        "bbox": [
            312.0,
            551.0,
            246.0,
            179.0
        ],
        "class": "Table"
    },
    {
        "bbox": [
            54.0,
            551.0,
            245.0,
            62.0
        ],
        "class": "Text"
    },
    {
        "bbox": [
            54.0,
            457.0,
            245.0,
            86.0
        ],
        "class": "Text"
    },
    {
        "bbox": [
            54.0,
            411.0,
            245.0,
            36.0
        ],
        "class": "Text"
    },
    {
        "bbox": [
            312.0,
            410.0,
            246.0,
            121.0
        ],
        "class": "Text"
    },
    {
        "bbox": [
            53.0,
            368.0,
            505.0,
            37.0
        ],
        "class": "Text"
    },
    {
        "bbox": [
            501.0,
            132.0,
            51.0,
            21.0
        ],
        "class": "Title"
    },
    {
        "bbox": [
            446.0,
            132.0,
            51.0,
            21.0
        ],
        "class": "Title"
    },
    {
        "bbox": [
            334.0,
            132.0,
            43.0,
            28.0
        ],
        "class": "Title"
    },
    {
        "bbox": [
            279.0,
            132.0,
            51.0,
            21.0
        ],
        "class": "Title"
    },
    {
        "bbox": [
            168.0,
            132.0,
            42.0,
            28.0
        ],
        "class": "Title"
    },
    {
        "bbox": [
            113.0,
            132.0,
            51.0,
            21.0
        ],
        "class": "Title"
    }
]